j.py
jshort-1.1.2.dist-info/LICENSE
jshort-1.1.2.dist-info/METADATA
jshort-1.1.2.dist-info/WHEEL
jshort-1.1.2.dist-info/top_level.txt
jshort-1.1.2.dist-info/RECORD
