Metadata-Version: 2.1
Name: jshort
Version: 1.1.2
Summary: Json shorthand for python
Home-page: http://github.com/eregnier/j
Author: Eric Régnier
Author-email: utopman@gmail.com
License: MIT
Keywords: utility,json,tool
Platform: UNKNOWN
Classifier: Programming Language :: Python
Classifier: Programming Language :: Python :: 3
Classifier: Programming Language :: Python :: 3.3
Classifier: Programming Language :: Python :: 3.4
Classifier: Programming Language :: Python :: 3.5
Classifier: Programming Language :: Python :: 3.6
Classifier: Programming Language :: Python :: 3.7
Classifier: Programming Language :: Python :: Implementation :: PyPy
Classifier: Programming Language :: Python :: Implementation :: Jython
Classifier: Intended Audience :: Developers
Requires-Dist: pygments
Requires-Dist: jsonpath-ng
